{
    "coupon": [
        {
            "id": 673,
            "coupon_id": "673",
            "status": 3,
            "click_count": 0,
            "category_id": 45,
            "category_name": "Food",
            "name": "Coupon 539",
            "coupon_name": "Coupon 539",
            "name_cn": null,
            "description": null,
            "description_cn": null,
            "color": "#ff83a6",
            "type": "Cash",
            "hashtag": null,
            "cash_amount": 3.0,
            "percentage": null,
            "gift1": null,
            "gift2": null,
            "is_coupon_none": 1,
            "amount": 0.0,
            "is_specific_item": "0",
            "when_purchasing": "任何一件增量版珍寶御結，再加購一件$18或以上御結",
            "regular_price": 0.0,
            "discount_price": 0.0,
            "quantity": 0,
            "purchasing_amount": 0.0,
            "expiry_date": "2024-11-30",
            "expiry_time": "12:00:00",
            "expiry_datetime": "2024-11-30 12:00:00",
            "additional_terms": "* 凡購買任何一件增量版珍寶御結，再加購一件 $18 或以上御結都可以減 $3\r\n* 此優惠不可用於購買套餐\r\n* 此優惠不可與其他優惠同時使用\r\n* 加配的御結優惠只適用於 $18 或以上之御結款式（珍寶御結除外）\r\n* 每件增量版珍寶御結只限加配一件 $18 或以上御結",
            "additional_terms_cn": "* 凡購買任何一件增量版珍寶御結，再加購一件 $18 或以上御結都可以減 $3\r\n* 此優惠不可用於購買套餐\r\n* 此優惠不可與其他優惠同時使用\r\n* 加配的御結優惠只適用於 $18 或以上之御結款式（珍寶御結除外）\r\n* 每件增量版珍寶御結只限加配一件 $18 或以上御結",
            "area": "1",
            "selected_area": "11",
            "country_id": null,
            "state_id": null,
            "city_id": null,
            "territory": null,
            "latitude": null,
            "longitude": null,
            "image": "673db8bdd074b.jpg",
            "offer_image": "",
            "qr_image": "",
            "customer_limit": 99999,
            "download_limit": 10,
            "is_restrict": false,
            "scan_count": 0,
            "is_scan_limit_reached": false,
            "added_from": 0,
            "vendor_id": 749,
            "vendor_name": "華御結 hana-musubi",
            "vendor_profile": "https://redsparkte.a2hosted.com/coupon_go_v2/storage/app/public/images/merchant/796/logo/673d5ca66cd6c.jpeg",
            "vendor_country": null,
            "vendor_state": null,
            "vendor_city": null,
            "vendor_street_address": "新界荃灣蕙荃路22-66號1G17鋪",
            "vendor_latitude": null,
            "vendor_longitude": null,
            "distance": null,
            "is_coupon_favorite": 0,
            "is_shop_favorite": 0,
            "is_coupon_used": 0,
            "is_limited_notification": 0,
            "created_by": 749,
            "branch_id": 0,
            "branch_id_temp": "0",
            "branch_parent": 0,
            "branch_count": 0,
            "has_branch": 0,
            "updated_by": 1,
            "launching_date": "2024-11-20",
            "created_at": "2024-11-20 18:23:57",
            "updated_at": "2024-11-30 12:15:04",
            "remaining_qr_code": 0,
            "coupon_offer_text": null,
            "coupon_short_description": null
        }
    ]
}